{"cameraMode":{"drawMode":0,"name":"Shaded","section":"Shading Mode"},"sceneLighting":true,"audioPlay":false,"sceneViewState":{"m_AlwaysRefresh":false,"showFog":true,"showSkybox":true,"showFlares":true,"showImageEffects":true,"showParticleSystems":true,"showVisualEffectGraphs":true,"m_FxEnabled":true},"in2DMode":false,"pivot":{"x":0.09057244658470154,"y":3.051692247390747,"z":-0.03999999165534973},"rotation":{"x":0.08382503688335419,"y":-0.0445081926882267,"z":-0.0037183277308940889,"w":-0.9955574870109558},"size":1.3986867666244507,"orthographic":false}